{"forum": {"content": "FB\uff1a\u4f55\u745c\u5a9b<br />\u5feb\u4f86\u52a0\u6211\u804a\u5929\u5440\ud83d\udc93\ud83d\udc93", "images": ["http://filestoresg1.beetalkmobile.com:8081/file/66095eefef6eec6f68b80cab89277e32"], "urls": [], "title": "\u55e8\u55e8\ud83d\ude0d"}, "threadStatus": 0, "regionId": 886, "barStatus": 0, "barId": 205, "postBy": {"utc": 1484070306000, "level": 1, "location": "\u53f0\u5317\u5e02\u00b7\u53f0\u7063", "avatar": "http://filestoresg1.beetalkmobile.com:8081/file/6336383258505181953", "name": "\u745c\ud83c\udf39"}, "id": 5193705}
