{"forum": {"content": "\u771f\u5fc3\u4ea4\u53cb   \u4e0d\u5df2\u8b80\u4e0d\u56de<br />\u8acb\u81ea\u5df1\u9001\u51fa\u9080\u8acb\u5466", "images": ["http://filestoresg1.beetalkmobile.com:8081/file/7c15ae70e3e69b8e4907645e083feb1f", "http://filestoresg1.beetalkmobile.com:8081/file/62133629ddd917d7ee64206e9e01567e"], "urls": [], "title": "#\u6c42\u812b\u9b6f"}, "threadStatus": 1, "regionId": 886, "barStatus": 0, "barId": 205, "postBy": {"utc": 1482375553000, "level": 1, "location": "\u5609\u7fa9\u7e23\u00b7\u53f0\u7063", "avatar": "http://filestoresg1.beetalkmobile.com:8081/file/4820081975276897024", "name": "\u6a80\u9999"}, "id": 5080203}
