{"forum": {"content": "\u9047\u5230\u4e86\u5fc3\u5100\u7684\u5973\u5b69<br />\u537b\u53c8\u4e0d\u77e5\u9053\u8a72\u600e\u9ebc\u958b\u53e3<br />\u5509  <br />\u771f\u7684\u662f\u4e0d\u77e5\u9053\u8a72\u600e\u9ebc\u8fa6  <br />\u8981\u5982\u4f55\u64fa\u812b\u55ae\u8eab", "images": ["http://filestoresg1.beetalkmobile.com:8081/file/2b3c3ae5f4da94a470d2cd61d3210ba2", "http://filestoresg1.beetalkmobile.com:8081/file/28436ba2936427ed403a6cf24d47796b"], "urls": [], "title": "\u4e0d\u77e5\u6240\u63aa"}, "threadStatus": 0, "regionId": 886, "barStatus": 0, "barId": 205, "postBy": {"utc": 1486361249000, "level": 15, "location": "\u53f0\u4e2d\u5e02\u00b7\u53f0\u7063", "avatar": "http://filestoresg1.beetalkmobile.com:8081/file/8843831623019943936", "name": "\u5c71\u5906"}, "id": 5342765}
