{"forum": {"content": "\u73ed\u4ee3\u8ddf\u6211\u8aaa\u7562\u696d\u7d00\u5ff5\u518a \u4e94\u6708\u4efd\u53ef\u4ee5\u62ff<br />\u5c31\u5feb\u7d50\u675f\u4e86 \u771f\u4e0d\u77e5\u9053\u54ea\u4e00\u5929\u53ef\u4ee5\u62ff", "images": ["http://filestoresg1.beetalkmobile.com:8081/file/76028cb14efce1cabad9b9fb022ead8d"], "urls": [], "title": "\u7562\u696d\u7d00\u5ff5\u518a"}, "threadStatus": 0, "regionId": 886, "barStatus": 0, "barId": 757, "postBy": {"utc": 1495960843000, "level": 1, "location": "", "avatar": "http://filestoresg1.beetalkmobile.com:8081/file/7499820493835395639", "name": "Uiki"}, "id": 5994284}
