{"forum": {"content": "\u4e0d\u77e5\u9053\u5927\u5bb6\u6709\u6c92\u6709\u89ba\u5f97\u55ae\u8eab\u5f88\u81ea\u7531<br />\u4f46\u6709\u6642\u53c8\u89ba\u5f97\u5b64\u55ae\u5462\ud83e\udd14", "images": ["http://filestoresg1.beetalkmobile.com:8081/file/b75be87020c3cb1473155b983cd39dcc"], "urls": [], "title": "\u55ae\u8eab"}, "threadStatus": 0, "regionId": 886, "barStatus": 0, "barId": 205, "postBy": {"utc": 1492444301000, "level": 1, "location": "\u53f0\u4e2d\u5e02\u00b7\u53f0\u7063", "avatar": "http://filestoresg1.beetalkmobile.com:8081/file/6358923263639856640", "name": "\u51f1 \u5929\u5e73\u5ea7"}, "id": 5752757}
