{"forum": {"content": "\u8981\u8d95\u5feb\u7761\u89ba\u4e86\uff0c\u7761\u89ba\u5b8c\u9084\u8981\u5012\u5783\u573e\uff0c\u8207\u5bf6\u8c9d\u4e00\u8d77\u7761\u89ba", "images": ["http://filestoresg1.beetalkmobile.com:8081/file/df56bac2913c86f057cc1c39b49fad70"], "urls": [], "title": "\u5439\u51b7\u6c23"}, "threadStatus": 0, "regionId": 886, "barStatus": 0, "barId": 767, "postBy": {"utc": 1495698690000, "level": 3, "location": "\u5f70\u5316\u7e23\u00b7\u53f0\u7063", "avatar": "http://filestoresg1.beetalkmobile.com:8081/file/7499820493835395639", "name": "Uiki"}, "id": 5976787}
