{"forum": {"content": "\u4e0d\u7ba1\u6c34\u6e96\u591a\u9ad8<br />\u9019\u7537\u751fpo<br />\u9b3c\u624d\u7406\u59b3= =<br />\u8981\u4e00\u8d77\u81ea\u52a0<br />\u6211\u5f88\u96f7 \u5f88\u611b\u54c8\u62c9 \u800d\u5ee2 ", "images": ["http://filestoresg1.beetalkmobile.com:8081/file/6f9ec4d38dddfa890a88c4c901ebd0b1"], "urls": [], "title": "ID\u8475\u6069\u600e\u9ebc\u98db"}, "threadStatus": 1, "regionId": 886, "barStatus": 0, "barId": 60, "postBy": {"utc": 1487114773000, "level": 1, "location": "\u5b9c\u862d\u7e23\u00b7\u53f0\u7063", "avatar": "http://filestoresg1.beetalkmobile.com:8081/file/-1509515098805986041", "name": "172"}, "id": 5394787}
