{"forum": {"content": "\u6703\u4e0d\u6703\u6709\u59ca\u59ca\u611b\u6211\u5462\uff1f", "images": ["http://filestoresg1.beetalkmobile.com:8081/file/2d87e1070f6a6cbaea8528aa2185fb02"], "urls": [], "title": "\u9019\u500b\u7684\u5c0f\u7537\u5b69\u3002"}, "threadStatus": 0, "regionId": 886, "barStatus": 0, "barId": 734, "postBy": {"utc": 1488830054000, "level": 2, "location": "", "avatar": "http://filestoresg1.beetalkmobile.com:8081/file/-3092762380522859261", "name": "\u2728\u5099\u80ce\u2728\u9b3c\u9b3c"}, "id": 5507819}
