{"forum": {"content": "\u6bcf\u5e74\u6700\u671f\u5f85\u7684\u5c31\u662f\u8ddf\u5927\u5b78\u6b7b\u9ee8\u5011\u4e00\u5e74\u4e00\u5ea6\u7684\u6eab\u6cc9\u884c\uff0c\u7576\u5927\u5bb6\u90fd\u6709\u5bb6\u5ead\u5f8c\u53ef\u80fd\u5c31\u6c92\u9019\u6a23\u7684\u6a5f\u6703\u4e86", "images": ["http://filestoresg1.beetalkmobile.com:8081/file/489ca26b6c4a19b47ece9930cfa43742", "http://filestoresg1.beetalkmobile.com:8081/file/5541af1e2376efc6f66977df94ef1189", "http://filestoresg1.beetalkmobile.com:8081/file/467384b7e259f302ca9b26847a67c4ec", "http://filestoresg1.beetalkmobile.com:8081/file/3f51d18bf21fe4e4cac4e3e3a7ef7446"], "urls": [], "title": "\u5b9c\u862d"}, "threadStatus": 1, "regionId": 886, "barStatus": 0, "barId": 684, "postBy": {"utc": 1482243408000, "level": 1, "location": "\u5b9c\u862d\u7e23\u00b7\u53f0\u7063", "avatar": "http://filestoresg1.beetalkmobile.com:8081/file/4969807958240164554", "name": "\u5b89\u514b"}, "id": 5071236}
