{"forum": {"content": "\u53f0\u5357\u6709\u5047\u65e5\u63a8\u85a6\u7684\u591c\u5e02\u55ce\uff1f\u8b1d\u8b1d", "images": ["http://filestoresg1.beetalkmobile.com:8081/file/abcc0ce93524a7f5c6c585a7e6a60cd4"], "urls": [], "title": "\u901b\u591c\u5e02"}, "threadStatus": 0, "regionId": 886, "barStatus": 0, "barId": 742, "postBy": {"utc": 1485943117000, "level": 1, "location": "\u96f2\u6797\u7e23\u00b7\u53f0\u7063", "avatar": "http://filestoresg1.beetalkmobile.com:8081/file/471951080911803881", "name": "\u5c0f\u77ee\u4eba"}, "id": 5314184}
