{"forum": {"content": "\u60f3\u4ea4\u500b\u670b\u53cb\u5462 ", "images": ["http://filestoresg1.beetalkmobile.com:8081/file/59d77b1c6f4f9f50c7f7a77068c19bd5", "http://filestoresg1.beetalkmobile.com:8081/file/f02bed3048504d4e17df3c446f38a551"], "urls": [], "title": "\u7121\u804a \u4ea4\u500b\u670b\u53cb\u5427"}, "threadStatus": 0, "regionId": 886, "barStatus": 0, "barId": 205, "postBy": {"utc": 1487324139000, "level": 1, "location": "\u9ad8\u96c4\u5e02\u00b7\u53f0\u7063", "avatar": "http://filestoresg1.beetalkmobile.com:8081/file/-1829088168790025997", "name": "Dreams"}, "id": 5408048}
