{"forum": {"content": "\u9019\u6a23\u62cd\u597d\u770b\u55ce\uff01", "images": ["http://filestoresg1.beetalkmobile.com:8081/file/a215a12269c043922ba66eb0c3a119ea", "http://filestoresg1.beetalkmobile.com:8081/file/225584f5c20fff3f6fffeec55037d08b", "http://filestoresg1.beetalkmobile.com:8081/file/2c0445f9428fbb1cc2a451e06e63f925"], "urls": [], "title": "\u884c\u8ecd\u53bb"}, "threadStatus": 1, "regionId": 886, "barStatus": 0, "barId": 4, "postBy": {"utc": 1495553516000, "level": 3, "location": "\u65b0\u5317\u5e02\u00b7\u53f0\u7063", "avatar": "http://filestoresg1.beetalkmobile.com:8081/file/-4592989921134594527", "name": "\u67da\u5b50\u59ae"}, "id": 5967686}
