{"forum": {"content": "\ud83d\ude04\ud83d\ude04\u6bdb\u5c0f\u5b69", "images": ["http://filestoresg1.beetalkmobile.com:8081/file/9a25f62b8a9efb813b42dc08b90fefac", "http://filestoresg1.beetalkmobile.com:8081/file/9e30ddbfd182027a146ea8cd1870225c"], "urls": [], "title": "\ud83d\ude04\ud83d\ude04"}, "threadStatus": 0, "regionId": 886, "barStatus": 0, "barId": 740, "postBy": {"utc": 1481315360000, "level": 2, "location": "\u65b0\u5317\u5e02\u00b7\u53f0\u7063", "avatar": "http://filestoresg1.beetalkmobile.com:8081/file/-7953513060783536452", "name": "\u3002\u3002\u3002\u3002\u3002\u3002\ud83d\ude31"}, "id": 5009407}
