{"forum": {"content": "\u5c08\u7528\u6a5f", "images": ["http://filestoresg1.beetalkmobile.com:8081/file/25a41cbf09bbd5182ab5109591034100", "http://filestoresg1.beetalkmobile.com:8081/file/e81c6a2c7d043172cfc503ce3d9f9dce", "http://filestoresg1.beetalkmobile.com:8081/file/d35979ae6d2eb6c12a92ff65c501320a"], "urls": [], "title": "\u96f7\u59c6\u5409\u7fc1\u514b"}, "threadStatus": 0, "regionId": 886, "barStatus": 0, "barId": 207, "postBy": {"utc": 1488385854000, "level": 9, "location": "\u65b0\u7af9\u7e23\u00b7\u53f0\u7063", "avatar": "http://filestoresg1.beetalkmobile.com:8081/file/-7943663641855436566", "name": "\u760b\u4e0d\u4e8c"}, "id": 5479624}
