{"forum": {"content": "\u5c04\u624b\u5ea7\u7684\u5973\u751f\u8a72\u600e\u9ebc\u8ffd??", "images": ["http://filestoresg1.beetalkmobile.com:8081/file/8f488f0372c96b6b2f96d8346d041ad2"], "urls": [], "title": "\u5c04\u624b\u5ea7\u7684\u5973\u751f\u8a72\u600e\u9ebc\u8ffd??"}, "threadStatus": 1, "regionId": 886, "barStatus": 0, "barId": 205, "postBy": {"utc": 1486399835000, "level": 2, "location": "\u5c4f\u6771\u7e23\u00b7\u53f0\u7063", "avatar": "http://filestoresg1.beetalkmobile.com:8081/file/-3183119127711596288", "name": "\u6c5f\u6c5f"}, "id": 5346447}
