{"forum": {"content": "\u6211\u7684\u662f<br />1.\u8d70\u97f3\u5929\u540e<br />2.\u591c\u884c\u52d5\u7269<br />3.\u5496\u5561\u611b\u60c5<br />4.\u6211\u4e0d\u662f\u6f58\u91d1\u84ee<br />\ud83d\ude18<br />\u5716\u7247\u70ba \u975e\u8aa0\u52ff\u64fe1 \u7247\u6bb5", "images": ["http://filestoresg1.beetalkmobile.com:8081/file/4fad8c75cac1ee63c014c2c64afa9e2b"], "urls": [], "title": "\u5927\u5bb6\u4f86\u8aaa\u8aaa\u4f602016\u4ee5\u4f86\u6700\u611b\u96fb\u5f71\u524d\u56db\u540d"}, "threadStatus": 0, "regionId": 886, "barStatus": 0, "barId": 47, "postBy": {"utc": 1484655932000, "level": 17, "location": "", "avatar": "http://filestoresg1.beetalkmobile.com:8081/file/1974544777909370906", "name": "\u3002\u3002"}, "id": 5232684}
