{"forum": {"content": "\u627e\u500b\u4eba\u966a\u6211\u904e\u500b\u55ae\u8eab\u60c5\u4eba\u7bc0\u5566\u54ed\u54ed", "images": ["http://filestoresg1.beetalkmobile.com:8081/file/60e8ff5e605055b7446e076301f5a31d"], "urls": [], "title": "\u60c5\u4eba\u7bc0\u4e00\u500b\u4eba\u904e\u55ce\uff1f"}, "threadStatus": 0, "regionId": 886, "barStatus": 0, "barId": 205, "postBy": {"utc": 1486757939000, "level": 1, "location": "\u9ad8\u96c4\u5e02\u00b7\u53f0\u7063", "avatar": "http://filestoresg1.beetalkmobile.com:8081/file/5701863899025129569", "name": "\u9b51\u9b45\u9b4d\u9b4e"}, "id": 5370297}
