{"forum": {"content": "\u5609\u7fa9", "images": ["http://filestoresg1.beetalkmobile.com:8081/file/7bb39f2475c44c5f56f090e7ab5751fc", "http://filestoresg1.beetalkmobile.com:8081/file/a33b25e1bc40dc6fb0357b3cd1107cae", "http://filestoresg1.beetalkmobile.com:8081/file/33b5f7a3d70f38456390433deda538fb", "http://filestoresg1.beetalkmobile.com:8081/file/da0edd3b80c790771171c06cb1b62968", "http://filestoresg1.beetalkmobile.com:8081/file/17c9e1799be6520c015fe9f8b203e3bd", "http://filestoresg1.beetalkmobile.com:8081/file/96e65efaec3e1f631d5e7e7aae2c9717"], "urls": [], "title": "\u5609\u7fa9"}, "threadStatus": 0, "regionId": 886, "barStatus": 0, "barId": 77, "postBy": {"utc": 1486776878000, "level": 8, "location": "\u65b0\u7af9\u7e23\u00b7\u53f0\u7063", "avatar": "http://filestoresg1.beetalkmobile.com:8081/file/139381796382123321", "name": "Jerry"}, "id": 5370863}
