{"forum": {"content": "  \u5916\u8868\u91cd\u8981\u55ce\uff1f<br />  \u5973\u4eba\u90fd\u611b\u6709\u9322\u7684\u55ce\uff1f<br />  ", "images": ["http://filestoresg1.beetalkmobile.com:8081/file/5280817a1c694c088045d03fab6f7b09", "http://filestoresg1.beetalkmobile.com:8081/file/698ad61ed2515f9b0504f556436365a0"], "urls": [], "title": "\u7e3d\u662f\u4e00\u500b\u4eba"}, "threadStatus": 0, "regionId": 886, "barStatus": 0, "barId": 205, "postBy": {"utc": 1491657661000, "level": 0, "location": "\u9ad8\u96c4\u5e02\u00b7\u53f0\u7063", "avatar": "http://filestoresg1.beetalkmobile.com:8081/file/-8362346658691609833", "name": "\u5289\u5049"}, "id": 5699375}
