{"forum": {"content": "\u5708\u5167\u4eba\u90fd\u4f86\u8a8d\u8b58", "images": ["http://filestoresg1.beetalkmobile.com:8081/file/36c365eb2b726e77ec28333d76d5ea7f"], "urls": [], "title": "T/P"}, "threadStatus": 0, "regionId": 886, "barStatus": 0, "barId": 383, "postBy": {"utc": 1490168621000, "level": 3, "location": "\u9ad8\u96c4\u5e02\u00b7\u53f0\u7063", "avatar": "http://filestoresg1.beetalkmobile.com:8081/file/-1235244120489026672", "name": "    \u0ca0 .\u032e\u0cb0\u0cc3 Nai"}, "id": 5597332}
