{"forum": {"content": "\u4efb\u4f55\u6771\u897f\u90fd\u53ef\u5e6b\u4f60\u627e 12\u865f\u3479\u51fa\u767c \u6b61\u8fce\u8a62\u554f", "images": [], "urls": [{"url": "https://www.facebook.com/Dec25%E5%B0%8F%E8%88%96%E6%97%A5%E6%9C%AC%E4%BB%A3%E8%B3%BC-1043751245771303/", "thumbUrl": "", "description": "", "title": "Security Check Required"}], "title": "Dec~25\u65e5\u672c\u4ee3\u8cfc \u96fb\u5668 \u670d\u98fe \u516c\u4ed4"}, "threadStatus": 0, "regionId": 886, "barStatus": 0, "barId": 87, "postBy": {"utc": 1483966909000, "level": 1, "location": "\u53f0\u5317\u5e02\u00b7\u53f0\u7063", "avatar": "http://filestoresg1.beetalkmobile.com:8081/file/6628789578631205412", "name": "\u963f\u6587"}, "id": 5186034}
