{"forum": {"content": "\u5b89\u5b89<br />\u9019\u88e1\u662f\u53f0\u4e2dcoser<br />\u7576\u7136\u4e3b\u8dd1\u53f0\u4e2d\u5834<br />\u56e0\u51fa\u89d2\u6b21\u6578\u4e0d\u591a<br />\u6240\u4ee5\u51fa\u9053\u6c92\u6709\u5f88\u597d<br />\u8acb\u898b\u91cf<br />\u5e0c\u671b\u80fd\u8a8d\u8b58\u66f4\u591a\u53f0\u4e2dcoser<br />\u4e5f\u8acb\u591a\u591a\u6307\u6559<br />", "images": ["http://filestoresg1.beetalkmobile.com:8081/file/0b007d20281f2fe1b88b5d4239256c44", "http://filestoresg1.beetalkmobile.com:8081/file/e4c53977af81ab133b8011e2a749484c", "http://filestoresg1.beetalkmobile.com:8081/file/1902c5f0855556449c54b7f9674a5147", "http://filestoresg1.beetalkmobile.com:8081/file/12e60e21750ad7a82aa8f93073c978b1", "http://filestoresg1.beetalkmobile.com:8081/file/8dbf322682aac34aea95da6f32f8a378"], "urls": [], "title": "\u521d\u6b21\u4ecb\u7d39"}, "threadStatus": 0, "regionId": 886, "barStatus": 0, "barId": 34, "postBy": {"utc": 1492780147000, "level": 2, "location": "", "avatar": "http://filestoresg1.beetalkmobile.com:8081/file/6317381497511055198", "name": "Nakako"}, "id": 5777003}
