{"forum": {"content": "\u4ea4\u500b\u670b\u53cb\u597d\u55ce\uff1f<br />\u51fa\u6c92\u5c4f\u6771\u6771\u6e2f\u5730\u5340\ud83d\ude02\ud83d\ude02", "images": ["http://filestoresg1.beetalkmobile.com:8081/file/ebebeaca2579077c392d2088ba7b1099"], "urls": [], "title": "\u908a\u7de3\u4eba\u6c92\u670b\u53cb"}, "threadStatus": 0, "regionId": 886, "barStatus": 0, "barId": 20, "postBy": {"utc": 1483878815000, "level": 1, "location": "\u5c4f\u6771\u7e23\u00b7\u53f0\u7063", "avatar": "http://filestoresg1.beetalkmobile.com:8081/file/2736525033709788161", "name": "\u838a"}, "id": 5179761}
