{"forum": {"content": "\u81ea\u7531\u5f0f\u81ea\u5b78\u4e00\u76f4\u6c92\u6709\u9032\u6b65<br /><br />\u600e\u9ebc\u6e38\u600e\u9ebc\u8e22\u90fd\u4e0d\u6703\u524d\u9032<br /><br />\u53cd\u800c\u8173\u90fd\u5f80\u4e0b\u6c89<br /><br />\u7121\u5948\u7684\u6211\u53ea\u80fd\u4e00\u76f4\u7576\u9752\u86d9\u738b\u5b50<br /><br />\u6709\u4eba\u80fd\u6559\u6211\u55ce<br /><br />\u6211\u53ea\u80fd\u7df4\u9031\u65e5<br /><br />\u6211\u60f3\u5b78\u6703\u81ea\u7531<br /><br />\u624d\u80fd\u6709\u6a5f\u6703\u4e0a\u9812\u734e\u53f0", "images": ["http://filestoresg1.beetalkmobile.com:8081/file/996ab62a5870738d8dead1349eed4f0c"], "urls": [], "title": "\u8dea\u6c42\u6709\u5fc3\u4eba\u6559\u6211\u81ea\u7531\u5f0f"}, "threadStatus": 0, "regionId": 886, "barStatus": 0, "barId": 66, "postBy": {"utc": 1487016903000, "level": 5, "location": "\u65b0\u5317\u5e02\u00b7\u53f0\u7063", "avatar": "http://filestoresg1.beetalkmobile.com:8081/file/-1707969264099828207", "name": "\ud83d\udee0Shih Cheng You\ud83d\udeb4\ud83c\udffd"}, "id": 5388376}
