{"forum": {"content": "\u5e0c\u671b\u660e\u5929\u7684\u5929\u6c23\u4e00\u6a23\u8d85\u7d1a\u597d<br />\u8ddf\u5fc3\u60c5\u4e00\u6a23\u7f8e\u9e97\u2764", "images": ["http://filestoresg1.beetalkmobile.com:8081/file/866f72187d3822651c2d3b0fdbd8f785"], "urls": [], "title": "\u7948\u6c42\u597d\u5929\u6c23"}, "threadStatus": 0, "regionId": 886, "barStatus": 0, "barId": 4, "postBy": {"utc": 1487526404000, "level": 1, "location": "\u5b9c\u862d\u7e23\u00b7\u53f0\u7063", "avatar": "http://filestoresg1.beetalkmobile.com:8081/file/-1909511927257476352", "name": "Abbie"}, "id": 5422489}
