{"forum": {"content": "\u5e36\u6211\u8d70\u8ab0\u8981\u628a\u6211\u5e36\u8d70(\u9650T)", "images": ["http://filestoresg1.beetalkmobile.com:8081/file/a54634af5fa54795321312856d5863ca"], "urls": [], "title": "\u597d\u76f8\u8655"}, "threadStatus": 0, "regionId": 886, "barStatus": 0, "barId": 20, "postBy": {"utc": 1485114249000, "level": 5, "location": "\u65b0\u5317\u5e02\u00b7\u53f0\u7063", "avatar": "http://filestoresg1.beetalkmobile.com:8081/file/1662362643707511499", "name": "\u742a\u742a"}, "id": 5263003}
