{"forum": {"content": "\u5e78\u798f\u6642\u523b \uff01\uff01\u809a\u5b50\u9913\u7684\u6642\u5019 \u6709\u6771\u897f\u5403", "images": ["http://filestoresg1.beetalkmobile.com:8081/file/f0435ff81109ae24d8a92e36cf985d21", "http://filestoresg1.beetalkmobile.com:8081/file/72c49dbc127ea8cea49779d0d0f8693f", "http://filestoresg1.beetalkmobile.com:8081/file/eec9171bd540feb840f6472b3017ef1c"], "urls": [], "title": "\u65e9\u9910"}, "threadStatus": 0, "regionId": 886, "barStatus": 0, "barId": 707, "postBy": {"utc": 1495842848000, "level": 6, "location": "", "avatar": "http://filestoresg1.beetalkmobile.com:8081/file/5962130408078430234", "name": "\u8521\u9298\u8ce2"}, "id": 5986168}
