{"forum": {"content": "\u540c\u984c", "images": ["http://filestoresg1.beetalkmobile.com:8081/file/a8023fc8e1d789ac42f501250547bd9b", "http://filestoresg1.beetalkmobile.com:8081/file/1e47bf7beb16828fb6a84ade2b3bd525", "http://filestoresg1.beetalkmobile.com:8081/file/8b3195576a5a209f9375da0c8c7d4d37", "http://filestoresg1.beetalkmobile.com:8081/file/6f905f0215e2831e1329b167f9557b09", "http://filestoresg1.beetalkmobile.com:8081/file/0d90604433864be17506642a46b24a6a"], "urls": [], "title": "\u90a3\u500b\u597d\u770b\uff1f\u6700\u8fd1\u9aee\u578b\u548c\u984f\u8272\u4e00\u76f4\u8b8a\ud83d\ude02\u597d\u723d"}, "threadStatus": 0, "regionId": 886, "barStatus": 0, "barId": 4, "postBy": {"utc": 1490284769000, "level": 2, "location": "\u65b0\u754c\u00b7\u9999\u6e2f", "avatar": "http://filestoresg1.beetalkmobile.com:8081/file/284143513613894912", "name": "Kel"}, "id": 5606107}
