{"forum": {"content": "\u6709\u4eba\u8aaa\u91d1\u725b\u5f88\u56fa\u57f7<br />\u6211\u60f3\u77e5\u9053\u56fa\u57f7\u5728\u54ea<br />\u91d1\u725b\u9069\u5408\u7684\u661f\u5ea7?<br />\u6709\u4eba\u80fd\u89e3\u7b54\u55ce", "images": ["http://filestoresg1.beetalkmobile.com:8081/file/bd5fd74e623f33592b38a60fb9f8747a"], "urls": [], "title": "\u91d1\u725b\u7537"}, "threadStatus": 0, "regionId": 886, "barStatus": 0, "barId": 88, "postBy": {"utc": 1484475514000, "level": 3, "location": "\u9ad8\u96c4\u5e02\u00b7\u53f0\u7063", "avatar": "http://filestoresg1.beetalkmobile.com:8081/file/-5114888508513584381", "name": "\u963f\u4efb"}, "id": 5220103}
