{"forum": {"content": "\u9000\u4f0d\u4e86\u624d\u5347\u5b98\u2026\u2026\u256e(\u256f_\u2570)\u256d ", "images": ["http://filestoresg1.beetalkmobile.com:8081/file/79c972d628f48fdd239e41f832b74361"], "urls": [], "title": "\u6240\u8b02\u7684\u96e2\u7dda\u7d93\u9a57\u503c\u2026\u2026"}, "threadStatus": 0, "regionId": 886, "barStatus": 0, "barId": 704, "postBy": {"utc": 1492000236000, "level": 2, "location": "\u96f2\u6797\u7e23\u00b7\u53f0\u7063", "avatar": "http://filestoresg1.beetalkmobile.com:8081/file/4303886535510758804", "name": "\u4f4e\u8abf\u2649"}, "id": 5723178}
