{"forum": {"content": "\u5982\u984c", "images": ["http://filestoresg1.beetalkmobile.com:8081/file/d6c3863b023e5cba381b5effa60b7248"], "urls": [], "title": "\u57fa\u9686\u6709\u9700\u8981\u4fdd\u6bcd\u7684\u53ef\u4ee5\u79c1\u6211\u54e6"}, "threadStatus": 1, "regionId": 886, "barStatus": 0, "barId": 770, "postBy": {"utc": 1491827384000, "level": 9, "location": "\u57fa\u9686\u5e02\u00b7\u53f0\u7063", "avatar": "http://filestoresg1.beetalkmobile.com:8081/file/1952810737564887300", "name": "\u8431"}, "id": 5711084}
