{"forum": {"content": "\u6211\u5728\u96f2\u88e1\u6f2b\u6b65", "images": ["http://filestoresg1.beetalkmobile.com:8081/file/06769571ba380927a05ea90f6335146d", "http://filestoresg1.beetalkmobile.com:8081/file/0a8394ea558937b07d7b993558c94ca8", "http://filestoresg1.beetalkmobile.com:8081/file/dbe5b4ae2b319b5d7e9b9aaad4e1bcab", "http://filestoresg1.beetalkmobile.com:8081/file/cbd6f8aa40162eafc0ec4fe365881559", "http://filestoresg1.beetalkmobile.com:8081/file/e7ab8e3ea340ef689cb2661653bde734", "http://filestoresg1.beetalkmobile.com:8081/file/b2532eb768e50f0a66bed1c062cdc7c0"], "urls": [], "title": "\u5408\u6b61\u5c71 \u6b66\u5dba\u65e5\u843d"}, "threadStatus": 0, "regionId": 886, "barStatus": 0, "barId": 85, "postBy": {"utc": 1482145745000, "level": 1, "location": "\u65b0\u5317\u5e02\u00b7\u53f0\u7063", "avatar": "http://filestoresg1.beetalkmobile.com:8081/file/-292548156692345899", "name": "Rebecca"}, "id": 5064381}
