{"forum": {"content": "\u804a\u51fa\u611f\u60c5\u6211\u8ca0\u8cac", "images": ["http://filestoresg1.beetalkmobile.com:8081/file/cf7eea1edd2da197def0c0e11533d028"], "urls": [], "title": "\u7761\u4e0d\u8457\u5c31\u627e\u6211\u804a\u5929\u5427"}, "threadStatus": 1, "regionId": 886, "barStatus": 0, "barId": 205, "postBy": {"utc": 1495637398000, "level": 2, "location": "\u6843\u5712\u5e02\u00b7\u53f0\u7063", "avatar": "http://filestoresg1.beetalkmobile.com:8081/file/7935418432187791661", "name": "(\uffe3(\u25cf\u25cf)\uffe3)\u3000"}, "id": 5973381}
