{"forum": {"content": "\u5c08\u653b\"\u963f\u840a\u65af\u7279\"<br />\u6211\u4e0d\u6562\u8aaa\u591a\u5f37\uff0c\u4f46\u7a69\u5b9a\u6027\u9ad8<br />\u56e0\u70ba\u5c45\u4f4f\u5730\u95dc\u4fc2\uff0c<br />\u7db2\u8def\u8a0a\u865f\u6709\u6642\u5f88\u4e0d\u7a69\uff0c<br />\u5c0e\u81f4\u88ab\u8aa4\u8a8d\u70ba\u639b\u6a5f\uff0c<br />\u5e0c\u671b\u80fd\u627e\u4e00\u4e9b\u56fa\u5b9a\u7684\u73a9\u5bb6\u4e00\u8d77\u6253\uff0c<br />\u6709\u89c0\u5ff5\u4e0d\u5634\u4e92\u52a9\u5f88\u91cd\u8981\u3002<br />\u52a0\u597d\u53cb\u524d\u8acb\u544a\u77e5\u662f\u54ea\u88e1\u5f97\u77e5\u7684\u8a0a\u606f\u3002<br />\u8b1d\u8b1d\uff01", "images": ["http://filestoresg1.beetalkmobile.com:8081/file/a673c51ad4dd9000bbc012a5281e69ca"], "urls": [], "title": "\u5fb5\u6c42\u5f37\u529b\u968a\u53cb"}, "threadStatus": 0, "regionId": 886, "barStatus": 0, "barId": 59, "postBy": {"utc": 1492144533000, "level": 2, "location": "\u65b0\u5317\u5e02\u00b7\u53f0\u7063", "avatar": "http://filestoresg1.beetalkmobile.com:8081/file/-4844878135429394935", "name": "\u9713\ud83d\udc8b\u4e0d\u9a37\u7684\u9a37\u5973"}, "id": 5732096}
