{"forum": {"content": "\u59b9\u59b9\u6211\u7e3d\u662f\u88ab\u4eba\u8aaa\u7684\u597d\u50cf\u4e0d\u662f86\u751f\u7684XD", "images": ["http://filestoresg1.beetalkmobile.com:8081/file/136c6bdd714fcbd954ead5130e6a2cb9", "http://filestoresg1.beetalkmobile.com:8081/file/461afdad83cee679bcb002ca4c595281"], "urls": [], "title": "86\u5c3e\u4f86\u7684\u2026"}, "threadStatus": 1, "regionId": 886, "barStatus": 0, "barId": 748, "postBy": {"utc": 1489084071000, "level": 2, "location": "\u53f0\u4e2d\u5e02\u00b7\u53f0\u7063", "avatar": "http://filestoresg1.beetalkmobile.com:8081/file/-8019898264106743261", "name": "\u5b6b\u6dd1\u5a77."}, "id": 5524741}
