{"forum": {"content": "\u6500\u5ca9\u7661\uff0c\u6500\u5ca9\u72c2\uff0c\u6709\u6500\u5ca9\u7684\u4f86\u8a8d\u8b58\u4e00\u4e0b\u554a\uff01", "images": ["http://filestoresg1.beetalkmobile.com:8081/file/a5d6cfdcb300247f5c3f55f400d431b6"], "urls": [], "title": "\u6301\u7e8c\u6500\u5ca9\u4e2d"}, "threadStatus": 0, "regionId": 886, "barStatus": 0, "barId": 66, "postBy": {"utc": 1493691775000, "level": 2, "location": "\u9ad8\u96c4\u5e02\u00b7\u53f0\u7063", "avatar": "http://filestoresg1.beetalkmobile.com:8081/file/9014616580236587866", "name": "spiderbear"}, "id": 5840223}
