{"forum": {"content": "\u597d\u50cf\u5927\u90e8\u5206\u7684\u90fd\u8d70\u5149\u7642\u4e86<br />\u6c34\u6676\u597d\u50cf\u6c92\u4ec0\u9ebc\u4eba\u5728\u505a\uff1f\u70ba\u4ec0\u9ebc\u554a\uff1f<br />\u662f\u76f4\u63a5\u5ef6\u7532\u518d\u505a\u5149\u7642\u5c31\u53ef\u4ee5\u4e86\u55ce\uff1f<br /><br />\u7532\u8089\u5f88\u77ed\u61c9\u8a72\u8981\u505a\u6c34\u6676\uff1f\u9084\u662f\u5149\u7642\u5ef6\u7532\uff1f<br /><br />\u6700\u5f8c\uff0c\u6709\u4eba\u53ef\u4ee5\u5e73\u65e5\u7d04\u505a\u6307\u7532\u55ce\uff1f", "images": ["http://filestoresg1.beetalkmobile.com:8081/file/142ed2e851ea6fcc504fde8c12a2d269"], "urls": [], "title": "\u8acb\u554f\u6c34\u6676"}, "threadStatus": 0, "regionId": 886, "barStatus": 0, "barId": 733, "postBy": {"utc": 1489932825000, "level": 2, "location": "\u65b0\u5317\u5e02\u00b7\u53f0\u7063", "avatar": "http://filestoresg1.beetalkmobile.com:8081/file/611565962536448025", "name": "\u745e\u745e\u264c\ufe0f\ud83d\udc33 R\u20dfE\u20dfL\u20dfA\u20dfX\u20dfI\u20dfN\u20dfG\u20df"}, "id": 5581609}
