{"forum": {"content": "3/11\u8fa6\u751f\u65e5\u5728\u6797\u53e3\u6a02\u5a01<br />\u6709\u8208\u8da3\u53ef\u4ee5\u806f\u7d61\u6211<br />\u6b61\u8fce\u9080\u7d04\u4f60\u5011\u4e00\u540c\u53c3\u8207\u6211\u7684\u751f\u65e5<br />\u6211\u5f88\u611b\u4ea4\u670b\u53cb\u5973\u751f\u7537\u751f\u90fd\u53ef<br />\u4f46\u5973\u751f\u6700\u597d\ud83d\udc95\ud83d\udc95", "images": ["http://filestoresg1.beetalkmobile.com:8081/file/6d9f677679b6bbdc16c8cd2c2179b64b"], "urls": [], "title": "3/11\u9080\u7d04\u751f\u65e5\u6d3e\u5c0d"}, "threadStatus": 1, "regionId": 886, "barStatus": 0, "barId": 792, "postBy": {"utc": 1488457661000, "level": 1, "location": "\u65b0\u5317\u5e02\u00b7\u53f0\u7063", "avatar": "http://filestoresg1.beetalkmobile.com:8081/file/-7821810270255452408", "name": "\u54c6\u54c6"}, "id": 5483341}
