{"forum": {"content": "\u5982\u9898", "images": ["http://filestoresg1.beetalkmobile.com:8081/file/1613fd80319af44054a5fdd8bf550c81"], "urls": [], "title": "\u6211\u7684\u795e\u554a\uff01\u8cdc\u6211\u5e7e\u500b\u8ac7\u5fc3\u4ea4\u5fc3\u7684\u597d\u59ca\u59b9\u5504\uff01"}, "threadStatus": 0, "regionId": 886, "barStatus": 0, "barId": 20, "postBy": {"utc": 1488603886000, "level": 1, "location": "\u6843\u5712\u5e02\u00b7\u53f0\u6e7e", "avatar": "http://filestoresg1.beetalkmobile.com:8081/file/-7459792747369906929", "name": "\u5fc3\u513f"}, "id": 5491839}
