{"forum": {"content": "\u00df\u015bg \u5976\u9f3b\u0649  \u81ea\u52a0\u597d\u53cb\u56c9<br /><br />\u6211\u53ef\u4ee5\u7576\u4f60\u7684sup\u5466\u2764", "images": ["http://filestoresg1.beetalkmobile.com:8081/file/fe43bea18398ea6ced14a277556ce3b8", "http://filestoresg1.beetalkmobile.com:8081/file/3a8d84c126d0e104077b2d2c5ab90fe3"], "urls": [], "title": "\u5c0b\u627e\u50b3\u8aaa\u968a\u53cb\ud83d\ude4b"}, "threadStatus": 0, "regionId": 886, "barStatus": 0, "barId": 59, "postBy": {"utc": 1488173395000, "level": 2, "location": "\u6843\u5712\u5e02\u00b7\u53f0\u7063", "avatar": "http://filestoresg1.beetalkmobile.com:8081/file/-2436453975502621916", "name": "\ud83d\udc95"}, "id": 5465296}
