{"forum": {"content": "\u672c\u5b63\u7b2c\u4e00\u6b21\u6234\u6bdb\u5e3d\uff0c\u51b7\u6b7b\u4e86\u5566\uff01", "images": ["http://filestoresg1.beetalkmobile.com:8081/file/6788d7b1c3b0df915636b19ae6c6a10f", "http://filestoresg1.beetalkmobile.com:8081/file/7333670ce0c3444c9a8496aad61500eb"], "urls": [], "title": "\u5bd2\u6d41\u4f86\u8972\uff01"}, "threadStatus": 0, "regionId": 886, "barStatus": 0, "barId": 33, "postBy": {"utc": 1488284019000, "level": 9, "location": "\u53f0\u5317\u5e02\u00b7\u53f0\u7063", "avatar": "http://filestoresg1.beetalkmobile.com:8081/file/8935409954398131466", "name": "\u274c\u904e\u671f\u7684\u5c0f\u9bae\u8089\ud83c\udf56"}, "id": 5472703}
