{"forum": {"content": "\u4e00\u500b\u5f88\u68d2\u7684\u5730\u65b9\uff0c\u9760\u8fd1\u6c99\u5df4\u5927\u5b78<br />\u670b\u53cb\u5e6b\u5fd9\u62ff\u7684\uff0c\u4e00\u500b\u665a\u4e0a3500\u53f0\u5e63<br />\u4f46\u662f\u5468\u906d\u4ec0\u9ebc\u90fd\u6c92\u6709<br />\u81ea\u5df1\u53ef\u4ee5\u5e36\u6ce1\u9eb5\uff0c\u7ce7\u98df\uff0c\u6c34\u679c\uff0c\u98f2\u6599<br />\u56e0\u70ba\u6709\u670b\u53cb\u7172\u7684\u53cb\u60c5\u96de\u6e6f<br />\u4e00\u8d70\u51fa\u9662\u5b5020\u516c\u5c3a\u5c31\u662f\u5927\u6d77<br />", "images": ["http://filestoresg1.beetalkmobile.com:8081/file/dae25c5e50c3133aa9e2af0c58c1de64", "http://filestoresg1.beetalkmobile.com:8081/file/58a9475f94d447636c3217396d00f96b", "http://filestoresg1.beetalkmobile.com:8081/file/bf18ae8ed4951308e11c05f5f4113e92", "http://filestoresg1.beetalkmobile.com:8081/file/fcef79c0ff0b18f3f17bcda6f15bdc9a", "http://filestoresg1.beetalkmobile.com:8081/file/a3f2d08e70237d0918121d15f3ce7bde", "http://filestoresg1.beetalkmobile.com:8081/file/e09f77162e71fee8d07419208cde9911"], "urls": [], "title": "Kota Kinabalu Borneo Villa"}, "threadStatus": 0, "regionId": 886, "barStatus": 0, "barId": 85, "postBy": {"utc": 1486126072000, "level": 3, "location": "\u6c99\u5df4\u00b7\u99ac\u4f86\u897f\u4e9e", "avatar": "http://filestoresg1.beetalkmobile.com:8081/file/7748568505729175893", "name": "\u718a\u8c93\u773c"}, "id": 5326336}
