{"forum": {"content": "\u6c92\u4e0a\u73ed10\u9ede\u4e0a\uff0c\u6709\u4e0a\u73ed6.7\u9ede\u4e0a<br />\u5e0c\u671b\u60f3\u4e0a\u5206\u53ef\u4ee5\u4e00\u8d77\u73a9\u7684\u8acb\u7559id", "images": ["http://filestoresg1.beetalkmobile.com:8081/file/049a4e98e18f2809da8b7122f1a19535"], "urls": [], "title": "\u55ae\u96d9\u9285\u9280\u627e\u9577\u671f\u968a\u53cb"}, "threadStatus": 1, "regionId": 886, "barStatus": 0, "barId": 60, "postBy": {"utc": 1491876744000, "level": 2, "location": "\u6843\u5712\u5e02\u00b7\u53f0\u7063", "avatar": "http://filestoresg1.beetalkmobile.com:8081/file/-7148076808850725737", "name": "\u4e0d\u7528\u4e86"}, "id": 5714423}
