{"forum": {"content": "\u62ff\u8457\u75c5\u6b77\u8cc7\u6599\u5730\u5740\u8ddf\u8e64\u5230\u5bb6\uff0c\u5927\u5bb6\u66fe\u7d93\u6709\u9019\u6a23\u5b50\u7684\u7d93\u9a57\u55ce\uff1f", "images": ["http://filestoresg1.beetalkmobile.com:8081/file/358cba791530fce70bde44901b13cae7"], "urls": [], "title": "\u62ff\u8457\u75c5\u6b77\u8cc7\u6599\u5730\u5740\u8ddf\u8e64\u5230\u5bb6"}, "threadStatus": 1, "regionId": 886, "barStatus": 0, "barId": 18, "postBy": {"utc": 1488940475000, "level": 2, "location": "\u6843\u5712\u5e02\u00b7\u53f0\u7063", "avatar": "http://filestoresg1.beetalkmobile.com:8081/file/5984668186204870814", "name": "\u4ec7  \u96f2"}, "id": 5514308}
