{"forum": {"content": "\u4f46\u662f\u53ef\u4ee5\u8ddf\u6211\u9019\u500b\u919c\u5973\u8a8d\u8b58\u55ce\uff1f\ud83e\udd18\ud83e\udd18<br />", "images": ["http://filestoresg1.beetalkmobile.com:8081/file/6a423368421acbb2838a322f1de6547a"], "urls": [], "title": "\u6211\u4e0d\u662f\u5973\u795e\ud83d\ude02"}, "threadStatus": 0, "regionId": 886, "barStatus": 0, "barId": 32, "postBy": {"utc": 1492330607000, "level": 2, "location": "\u65b0\u5317\u5e02\u00b7\u53f0\u7063", "avatar": "http://filestoresg1.beetalkmobile.com:8081/file/5395652125085316612", "name": "\u738b\u6db5."}, "id": 5743981}
