{"forum": {"content": "\u7b2c\u4e00\u6b21\u73a9\u9019apps \u9084\u4e0d\u662f\u5f88\u6703\u7528 \u591a\u591a\u6307\u6559\u263a", "images": [], "urls": [{"url": "http://www.google.com", "thumbUrl": "https://www.google.com/logos/doodles/2017/100th-anniversary-of-giro-ditalia-6325612032557056.3-law.gif", "description": "Let the race begin! #GoogleDoodle", "title": "Google"}], "title": "\u5c0b\u627e4\u67082 \u540c\u65e5\u751f\u7684\u4eba\ud83d\ude0a"}, "threadStatus": 1, "regionId": 886, "barStatus": 0, "barId": 765, "postBy": {"utc": 1493978871000, "level": 1, "location": "\u9999\u6e2f", "avatar": "http://filestoresg1.beetalkmobile.com:8081/file/-9193673105775818027", "name": "Akira"}, "id": 5859508}
