{"forum": {"content": "\u60f3\u554f\u554f\u5927\u5bb6\uff0c\u5982\u679c\u4eca\u5929\u4f60\u662f\u5b78\u751f\u8eab\u5206\u7136\u5f8c\u53c8\u6709\u53e6\u4e00\u534a\uff0c\u4f46\u9019\u4ef6\u4e8b\u88ab\u73ed\u5c0e\u767c\u73fe\u4e5f\u8ddf\u5bb6\u9577\u8aaa\u4e86\uff0c\u5bb6\u9577\u53c8\u4e0d\u540c\u610f\u4f60\u5011\u4ea4\u5f80\u4f60\u5011\u6703\u600e\u9ebc\u505a\uff1f", "images": ["http://filestoresg1.beetalkmobile.com:8081/file/5db2923d0b01d3f34077b1776e0a002f"], "urls": [], "title": "\u3002\u3002"}, "threadStatus": 1, "regionId": 886, "barStatus": 0, "barId": 13, "postBy": {"utc": 1492261000000, "level": 1, "location": "\u6843\u5712\u5e02\u00b7\u53f0\u7063", "avatar": "http://filestoresg1.beetalkmobile.com:8081/file/8933484698707800180", "name": "Xuan"}, "id": 5739573}
