{"forum": {"content": "\u670b\u53cb\u8aaa\u6211\u9577\u7684\u50cf\u4e00\u7a2e\u72d7\uff0c\u4f60\u5011\u89ba\u5f97\u6709\u50cf\u54ea\u4e00\u7a2e\u55ce\uff1f<br />\u66f4\u591a\ud83d\udc36\u72d7\u7167<br />\ud83d\ude04\ud83d\ude04\ud83d\ude04\ud83d\ude04\ud83d\ude04<br />Ig:coke.bb", "images": ["http://filestoresg1.beetalkmobile.com:8081/file/52563f47c5e7279811143660fdc49aed", "http://filestoresg1.beetalkmobile.com:8081/file/d9929eda9993c4431bf4aca7ea633d74", "http://filestoresg1.beetalkmobile.com:8081/file/e63101b21b85bd580acaaa016b15c054", "http://filestoresg1.beetalkmobile.com:8081/file/9f8f13dbe97e1ac30402c06959945ae4", "http://filestoresg1.beetalkmobile.com:8081/file/17a65b1eb54debb590daab3176a94fbd"], "urls": [], "title": "\u9577\u5f97\u50cf\ud83d\udc36\ud83d\udc36\u662f\u771f\u7684\u55ce\uff1f"}, "threadStatus": 0, "regionId": 886, "barStatus": 0, "barId": 4, "postBy": {"utc": 1495025304000, "level": 2, "location": "", "avatar": "http://filestoresg1.beetalkmobile.com:8081/file/6099845320932556298", "name": "\u76ae\u5361\u7532"}, "id": 5931687}
