{"forum": {"content": "\u55e8<br /><br />\u81fa\u4e2d\u8001\u4eba\u4e00\u679a<br />\u4f60\u5011\u5462\uff1f", "images": ["http://filestoresg1.beetalkmobile.com:8081/file/d9d832d1d2d7c67cc31037a8114b5ae4"], "urls": [], "title": "\u4ea4\u670b\u53cb"}, "threadStatus": 0, "regionId": 886, "barStatus": 0, "barId": 20, "postBy": {"utc": 1495021595000, "level": 6, "location": "\u53f0\u4e2d\u5e02\u00b7\u53f0\u7063", "avatar": "http://filestoresg1.beetalkmobile.com:8081/file/23023777413685761", "name": "B"}, "id": 5931369}
