{"forum": {"content": "\u55e8~\u8acb\u6c42\u795e\u4eba\u6559\u5065\u8eab~", "images": ["http://filestoresg1.beetalkmobile.com:8081/file/b7f6b40a7230eecc2f7e9f951135b02f"], "urls": [], "title": "\u8981\u8a8d\u8b58\u5c31\u4f86"}, "threadStatus": 0, "regionId": 886, "barStatus": 0, "barId": 4, "postBy": {"utc": 1486032412000, "level": 1, "location": "\u5609\u7fa9\u5e02\u00b7\u53f0\u7063", "avatar": "http://filestoresg1.beetalkmobile.com:8081/file/1869581002755632485", "name": "lilili"}, "id": 5320138}
