{"forum": {"content": "\u4e09\u500b\u5c0f\u5b69\u7684\u5927\u53d4\uff0c\u4ec0\u9ebc\u6642\u9593\u5587\u8cfd", "images": ["http://filestoresg1.beetalkmobile.com:8081/file/6a410bb45468b1832d77aea7b3d81ea5"], "urls": [], "title": "\u5927\u53d4"}, "threadStatus": 0, "regionId": 886, "barStatus": 0, "barId": 838, "postBy": {"utc": 1492845923000, "level": 0, "location": "\u65b0\u5317\u5e02\u00b7\u53f0\u7063", "avatar": "http://filestoresg1.beetalkmobile.com:8081/file/8320679609466988032", "name": "Fed"}, "id": 5781583}
