{"forum": {"content": "~I \u2665 Beetalk~m.me/null\u4f4d<br />\u7f6e10031289ggsshttp://www.cwb.gov.tw/V7/forecast/index2.htm", "images": ["http://filestoresg1.beetalkmobile.com:8081/file/4046debdbc68af24f4ac7a5fa1be4b25"], "urls": [], "title": "\u76dc\u7528\u5e33\u865f\u9760\u5317"}, "threadStatus": 1, "regionId": 886, "barStatus": 0, "barId": 391, "postBy": {"utc": 1485989143000, "level": 1, "location": "\u96f2\u6797\u7e23\u00b7\u53f0\u7063", "avatar": "http://filestoresg1.beetalkmobile.com:8081/file/5685549340706866435", "name": "\u554f"}, "id": 5317391}
