{"forum": {"content": "\u81f3\u5f9e27\u6b72\u55ae\u8eab\u4e4b\u5f8c \u2026\u2026<br /><br />\u5c31\u6eff\u8a0e\u53ad\u9047\u5230\u7bc0\u65e5\u2026<br /><br />\u56e0\u70ba\u5bb6\u4eba\u7e3d\u662f\u6703\u7121\u610f\u898b\u554f\u2026<br /><br />\u4f55\u6642\u5e36\u4eba\u56de\u5bb6\u770b\u770b\u2026<br /><br />\u6c92\u4eba\u9078,\u90a3\u4f86\u5f97\u7d50\u5a5a\u5e0c\u671b\u2026<br /><br /><br />\u5230\u9019\u5e74\u7d00\u4e86 ,\u9023\u500b\u4f34\u90fd\u662f\u5962\u671b\u2026<br /><br />", "images": ["http://filestoresg1.beetalkmobile.com:8081/file/6419897bb482a738df4d21cdb521bc9f"], "urls": [], "title": "\u6bcf\u9022\u7bc0\u65e5 \u5fc5\u88ab\u554f(\u904e\u5e74 \u60c5\u4eba\u7bc0\u7b49)"}, "threadStatus": 0, "regionId": 886, "barStatus": 0, "barId": 13, "postBy": {"utc": 1487733793000, "level": 2, "location": "\u9ad8\u96c4\u5e02\u00b7\u53f0\u7063", "avatar": "http://filestoresg1.beetalkmobile.com:8081/file/6630184863224875384", "name": "Question"}, "id": 5435736}
