{"forum": {"content": "\u6b61\u8fce\u4ea4\u53cb\u804a\u5929<br /><br />\u7537\u53cb\u5931\u8e64\u4e86 \u8ab0\u6709\u627e\u5230 \u55b5~<br />", "images": ["http://filestoresg1.beetalkmobile.com:8081/file/456967ef93386128d363d7587cb59006"], "urls": [], "title": "\u4ea4\u53cb\u804a\u5929"}, "threadStatus": 1, "regionId": 886, "barStatus": 0, "barId": 205, "postBy": {"utc": 1490520287000, "level": 2, "location": "\u6f8e\u6e56\u7e23\u00b7\u53f0\u7063", "avatar": "http://filestoresg1.beetalkmobile.com:8081/file/9187045290401745490", "name": "\ud83d\udc07"}, "id": 5621899}
