{"forum": {"content": "<br />\u7e3d\u8981\u7b49\u5f85\u9ec3\u660f\u5230\u4f86<br />\u624d\u6703\u5c55\u7fc5\u7ff1\u7fd4", "images": ["http://filestoresg1.beetalkmobile.com:8081/file/4f6c4a02a8eb49ce6a5a75f56edb5029"], "urls": [], "title": "\u5bc6\u6d85\u74e6\u7684\u8c93\u982d\u9df9 "}, "threadStatus": 0, "regionId": 886, "barStatus": 0, "barId": 734, "postBy": {"utc": 1489769582000, "level": 1, "location": "\u96f2\u6797\u7e23\u00b7\u53f0\u7063", "avatar": "http://filestoresg1.beetalkmobile.com:8081/file/-1680769531567799035", "name": "Timme"}, "id": 5570908}
