{"forum": {"content": "\u5ee2\u6587<br />\u6211\u53ea\u662f\u7761\u4e0d\u8457\u22ef\u54c8\u54c8", "images": ["http://filestoresg1.beetalkmobile.com:8081/file/22457a4b4da3adc940dda6bc36d939cc"], "urls": [], "title": "\u773c\u775b\u696d\u969c\u91cd"}, "threadStatus": 0, "regionId": 886, "barStatus": 0, "barId": 707, "postBy": {"utc": 1493062777000, "level": 3, "location": "\u53f0\u5357\u5e02\u00b7\u53f0\u7063", "avatar": "http://filestoresg1.beetalkmobile.com:8081/file/-4086820927494858748", "name": "\u58f9\u634c\u67d2"}, "id": 5798186}
