{"forum": {"content": "\u5443\u2026\u4e0d\u77e5\u9053\u8981\u8aaa\u4ec0\u9ebc\u8036\uff01   \u563b\u563b\uff0c\u8acb\u898b\u8ad2\uff0c\u8a5e\u7aae\u4e2d\u2026\u2026", "images": ["http://filestoresg1.beetalkmobile.com:8081/file/deb4afdeffa1e229a7570facddf48211", "http://filestoresg1.beetalkmobile.com:8081/file/25c36fc5cca8bd952a1406918cb8726e", "http://filestoresg1.beetalkmobile.com:8081/file/75ef41a4edab0c542d249bfbc88284d6", "http://filestoresg1.beetalkmobile.com:8081/file/bc3469e08a99833a520ba8938beef2fd", "http://filestoresg1.beetalkmobile.com:8081/file/5f6af498e7dcf2910fcb9ab72a293640"], "urls": [], "title": "\u7c43\u7403\u968a"}, "threadStatus": 0, "regionId": 886, "barStatus": 0, "barId": 65, "postBy": {"utc": 1486571871000, "level": 4, "location": "\u82b1\u84ee\u7e23\u00b7\u53f0\u7063", "avatar": "http://filestoresg1.beetalkmobile.com:8081/file/-6085564841414126148", "name": "\u5976\u5634 \ud83d\udebc\ud83d\udebc"}, "id": 5358124}
