{"forum": {"content": "\u7f8e\u5973\u5011\u4e00\u5b9a\u8981\u5c0f\u5fc3<br /><br />\u90a3\u4e9b\u8ffd\u59b3\u5011\u7684\u7537\u751f\u90fd\u53ea\u662f\u60f3\u8ddf\u59b3\u5011\u4e0a\u5e8a<br /><br />\u6211\u5c31\u4e0d\u4e00\u6a23<br /><br /> <br />  <br /> <br /> <br /> <br /> <br /><br /> <br /> <br /> <br /> <br /> <br /> <br /> <br /><br /> <br />\u6211\u8349\u5730\u4e5f\u884c\uff0c\u6c99\u767c\u4e5f\u884c\uff0c\u5eda\u623f\u3001\u967d\u53f0\u3001\u6a13\u68af\u3001\u9802\u6a13\uff0c\u6211\u90fd\u53ef\u4ee5\ud83d\ude02", "images": ["http://filestoresg1.beetalkmobile.com:8081/file/98cf9bcb51c546a3a2613f34b4ea665b"], "urls": [], "title": "\u5973\u5b69\u5011\u5fc5\u770b"}, "threadStatus": 0, "regionId": 886, "barStatus": 0, "barId": 205, "postBy": {"utc": 1489562537000, "level": 3, "location": "", "avatar": "http://filestoresg1.beetalkmobile.com:8081/file/-5326961211590649839", "name": "\ud83d\udc51\u8c6a\u8001\u516c\ud83d\udc95"}, "id": 5556517}
