{"forum": {"content": "\u8089\u8089\u5973\u8def\u904e\u800c\u5df2\ud83d\ude1c", "images": ["http://filestoresg1.beetalkmobile.com:8081/file/cfbe4a923af9a5680d06311285b4ac80"], "urls": [], "title": "\u55ae\u8eab\ud83d\ude48"}, "threadStatus": 0, "regionId": 886, "barStatus": 0, "barId": 383, "postBy": {"utc": 1484577924000, "level": 2, "location": "\u57fa\u9686\u5e02\u00b7\u53f0\u7063", "avatar": "http://filestoresg1.beetalkmobile.com:8081/file/1233780696852734271", "name": "\u96e8\u7948"}, "id": 5227747}
