{"forum": {"content": "\u53f0\u7063\u6700\u7f8e\u7684\u6b65\u9053\u22ef\u5361\u7802\u7911", "images": ["http://filestoresg1.beetalkmobile.com:8081/file/d31d2a0a96a5bffb041d5076e6d87681", "http://filestoresg1.beetalkmobile.com:8081/file/72ef90005a61861d0775dae18303036a", "http://filestoresg1.beetalkmobile.com:8081/file/0d1c8b2ae4f6336ea9e49faac3b591a0", "http://filestoresg1.beetalkmobile.com:8081/file/cbbb0ab69af1f9c8346427bf31cee6cb", "http://filestoresg1.beetalkmobile.com:8081/file/988ee539f6001f88427df8c0a21a0394"], "urls": [], "title": "\u5c31\u60f3\u81ea\u5df1\u8d70\u8d70#2"}, "threadStatus": 0, "regionId": 886, "barStatus": 0, "barId": 85, "postBy": {"utc": 1488003410000, "level": 2, "location": "\u82b1\u84ee\u7e23\u00b7\u53f0\u7063", "avatar": "http://filestoresg1.beetalkmobile.com:8081/file/-1059276083015378669", "name": "\u6db5\u6db5"}, "id": 5453827}
