{"forum": {"content": "\u7559id\u6211\u52a0\u59b3", "images": ["http://filestoresg1.beetalkmobile.com:8081/file/8756ac6e2bedfce208b6695fa4962641", "http://filestoresg1.beetalkmobile.com:8081/file/d4a279260bbb40c41b6c6fa74551bff1"], "urls": [], "title": "\u4f11\u5047\u5c31\u662f\u6253lol"}, "threadStatus": 0, "regionId": 886, "barStatus": 0, "barId": 60, "postBy": {"utc": 1495191782000, "level": 5, "location": "\u53f0\u4e2d\u5e02\u00b7\u53f0\u7063", "avatar": "http://filestoresg1.beetalkmobile.com:8081/file/-3197399602592102062", "name": "\u5b87\ud83c\udf80"}, "id": 5942484}
