{"forum": {"content": "\u73fe\u5728\u7576\u6cb9\u6f06\u5de5\u8eab\u6750 \u5c08\u696d\u90fd\u8981\u5230\u9054\u4e00\u500b\u5883\u754c", "images": ["http://filestoresg1.beetalkmobile.com:8081/file/9ab985db77c1452cd779d17d02054ea3"], "urls": [], "title": "\u6cb9\u6f06\u5de5\u9006\u8972\uff01"}, "threadStatus": 0, "regionId": 886, "barStatus": 0, "barId": 719, "postBy": {"utc": 1491846026000, "level": 4, "location": "\u5609\u7fa9\u7e23\u00b7\u53f0\u7063", "avatar": "http://filestoresg1.beetalkmobile.com:8081/file/-8410327146279011071", "name": "Ryan"}, "id": 5713069}
