{"forum": {"content": "\u4e0d\u770b\u984f\uff1f\u5c11\u9a19\u4eba\u4e86<br />\u4eba\u5bb6\u90fd\u8aaa\u7b2c\u4e00\u5370\u8c61\u5f88\u91cd\u8981<br />\u90a3\u4e0d\u5c31\u662f\u770b\u984f\u55ce\ud83d\ude02\uff1f", "images": ["http://filestoresg1.beetalkmobile.com:8081/file/f30efe874498137c4115eac37a621e5e", "http://filestoresg1.beetalkmobile.com:8081/file/4f84e09386c5248341685c4f952d0ada"], "urls": [], "title": "\ud83e\udd14"}, "threadStatus": 0, "regionId": 886, "barStatus": 0, "barId": 4, "postBy": {"utc": 1487448285000, "level": 2, "location": "", "avatar": "http://filestoresg1.beetalkmobile.com:8081/file/-698985927364421887", "name": "LH."}, "id": 5416699}
