{"forum": {"content": "\u795e\u7d93\u75c5\u55ce\uff1f \u5e79\u561b\u8981\u4e00\u76f4\u95dc\u6ce8\u59b3\uff1f \u770b\u5230\u59b3po\u7684\u53c8\u80fd\u600e\u6a23\uff1f\u6c92\u770b\u5230\u53c8\u600e\u6a23\uff1f\u597d\u7d2f \u4e0d\u77e5\u9053\u5728\u57f7\u8457\u4ec0\u9ebc\uff1f \u6bcf\u5929\u91cd\u8986\u8457\u60f3\u59b3 \u91cd\u8986\u8457\u95dc\u6ce8\u59b3 \u4ec0\u9ebc\u6642\u5019\u624d\u4e0d\u518d\u9019\u6a23\u641e\u81ea\u5df1\uff1f", "images": ["http://filestoresg1.beetalkmobile.com:8081/file/a355506e6c71cd0bef7be75edfc87a01"], "urls": [], "title": "\u5509\u2026"}, "threadStatus": 0, "regionId": 886, "barStatus": 0, "barId": 729, "postBy": {"utc": 1483456088000, "level": 1, "location": "\u5c4f\u6771\u7e23\u00b7\u53f0\u7063", "avatar": "http://filestoresg1.beetalkmobile.com:8081/file/-4487125623405863580", "name": "W\u00e9i zh\u00ec"}, "id": 5151564}
