{"forum": {"content": "\u9084\u662f\u756b\u7684\u5f88\u7c97\u7cd9\u5927\u5bb6\u5225\u4ecb\u610f\u554a<br />\u9019\u88e1\u9ad8\u624b\u592a\u591a\u4e86", "images": ["http://filestoresg1.beetalkmobile.com:8081/file/afd4b17e2fac3a729f3590fc7c26387c"], "urls": [], "title": "For you"}, "threadStatus": 1, "regionId": 886, "barStatus": 0, "barId": 35, "postBy": {"utc": 1482509693000, "level": 3, "location": "", "avatar": "http://filestoresg1.beetalkmobile.com:8081/file/6155409143885557505", "name": "\u8f9b\u9f4a\u5929"}, "id": 5089913}
