{"forum": {"content": "\u54c8\u56c9 \u6709\u4f4f\u81fa\u5317\u5e02\u9084\u662f\u65b0\u5317\u5e02\u7684\u5973\u751f\u670b\u53cb\u55ce\uff1f\u4f86\u4ea4\u500b\u670b\u53cb\u5427\uff01\u9650\u5b9a\u5973\u751f \u7537\u751f\u6b62\u6b65\u5566\u62b1\u6b49\ud83d\ude02\ud83d\ude02\ud83d\ude02", "images": ["http://filestoresg1.beetalkmobile.com:8081/file/ba20e15f7877e6f833258c8a20ca8282"], "urls": [], "title": "\u627e\u53f0\u5317\u65b0\u5317\u5973\u751f\u670b\u53cb"}, "threadStatus": 1, "regionId": 886, "barStatus": 0, "barId": 786, "postBy": {"utc": 1486062275000, "level": 2, "location": "\u65b0\u5317\u5e02\u00b7\u53f0\u7063", "avatar": "http://filestoresg1.beetalkmobile.com:8081/file/-5381402425934134268", "name": "Nung"}, "id": 5322769}
