{"forum": {"content": "\u6709\u4eba\u60f3\u8981\u4e00\u8d77\u8b8a\u7f8e\u7f8e\u5660\u55ce\ud83e\udd17\ud83e\udd17\ud83e\udd17", "images": ["http://filestoresg1.beetalkmobile.com:8081/file/2594f424322c28108107bb35832dc8c5"], "urls": [], "title": "\u6709\u4eba\u5c0d\u4fdd\u990a\u8b8a\u7f8e\u6709\u8208\u8da3\u55ce\uff1f"}, "threadStatus": 0, "regionId": 886, "barStatus": 0, "barId": 422, "postBy": {"utc": 1486616742000, "level": 1, "location": "\u53f0\u5357\u5e02\u00b7\u53f0\u7063", "avatar": "http://filestoresg1.beetalkmobile.com:8081/file/-1662277961594557184", "name": "cobie\u2764\ufe0f"}, "id": 5360281}
