{"forum": {"content": "\u8d85\u7f8e\u7684\uff0c\u53c8\u597d\u73a9", "images": ["http://filestoresg1.beetalkmobile.com:8081/file/eb0d7d00988677357be58907f9f36499", "http://filestoresg1.beetalkmobile.com:8081/file/2d0abe869ed8b96b3bcd19433f093baf", "http://filestoresg1.beetalkmobile.com:8081/file/ccc083d1ade499769c78023ddb8a10b6", "http://filestoresg1.beetalkmobile.com:8081/file/b6041fcf280d057d75f3157f94f4af61", "http://filestoresg1.beetalkmobile.com:8081/file/c17f887bb9bda99e8e5c0845a847a986", "http://filestoresg1.beetalkmobile.com:8081/file/7773b2cc0c3a53866b08c5283c9368da"], "urls": [], "title": "\u9ec3\u91d1&\u767d\u91d1\u5cfd\u8c37"}, "threadStatus": 0, "regionId": 886, "barStatus": 0, "barId": 604, "postBy": {"utc": 1494413300000, "level": 1, "location": "\u6843\u5712\u5e02\u00b7\u53f0\u7063", "avatar": "http://filestoresg1.beetalkmobile.com:8081/file/3701879733530876667", "name": "\u54c8\u5229\u738b\u5b50"}, "id": 5889608}
