{"forum": {"content": "\u4e09\u5fb7\u98ef\u5e97\u5411\u967d\u5ead<br /><br />\u70e4\u7684\u6fc3\u6fc3\u6d77\u5473\u7684~\u5929\u4f7f\u7d05\u8766!!!\u8d85\u8b9a", "images": ["http://filestoresg1.beetalkmobile.com:8081/file/1cdcce97b12d1a859768f7cbeb9c8278", "http://filestoresg1.beetalkmobile.com:8081/file/0a5fd91d35c890c7b8fab76f8b186ccd", "http://filestoresg1.beetalkmobile.com:8081/file/a28548d8ca8ba567e0ac53df9c544999"], "urls": [], "title": "\u7b2c\u4e00\u6b21\u4f86"}, "threadStatus": 0, "regionId": 886, "barStatus": 0, "barId": 98, "postBy": {"utc": 1493356859000, "level": 11, "location": "\u53f0\u5317\u5e02\u00b7\u53f0\u7063", "avatar": "http://filestoresg1.beetalkmobile.com:8081/file/-9152648128318888262", "name": "\u5ad1~justin~\u5ad1"}, "id": 5817957}
