{"forum": {"content": "\u6b61\u6a02\u4e0d\u5634", "images": ["http://filestoresg1.beetalkmobile.com:8081/file/b4e8a5c1c524a11bfa7f5673cff2399b"], "urls": [], "title": "++++\u4e00\u8d77\u6253\u50b3\u8aaa"}, "threadStatus": 0, "regionId": 886, "barStatus": 0, "barId": 59, "postBy": {"utc": 1485604049000, "level": 1, "location": "\u6843\u5712\u5e02\u00b7\u53f0\u7063", "avatar": "http://filestoresg1.beetalkmobile.com:8081/file/1680348454124764154", "name": "FB:\u9b4f\u4e16\u660c\uff08\u4e2d\u539f\u591c\u5e02\u6253\u96dc\uff09"}, "id": 5292712}
