{"forum": {"content": "\u56e0\u70ba\u7d93\u6fdf\u554f\u984c!!!<br /><br />\u8acb\u554f\u7576\u5175\u5230\u5e95\u597d\u4e0d\u597d<br />\u56e0\u70ba\u5feb\u9ad8\u4e2d\u7562\u696d\u4e86  \u8981\u8d95\u5feb\u505a\u6c7a\u5b9a<br />\u60f3\u554f\u554f\u5404\u4f4d\u7684\u610f\u898b<br />\u5f88\u591a\u4eba\u90fd\u8aaa\u88e1\u9762\u5f88\u6703\u52fe\u5fc3\u9b25\u89d2<br />\u4e5f\u6709\u4eba\u8aaa\u9760\u95dc\u4fc2\u9032\u53bb\u6bd4\u8f03\u597d\u4ec0\u9ebc\u7684<br /><br />\u6709\u5728\u60f3\u8981\u4e0d\u8981\u76f4\u63a5\u8003\u8ecd\u6821<br /><br />#\u5716\u6587\u4e0d\u7b26  \u8acb\u5ffd\u7565\u7167\u7247\ud83d\ude02", "images": ["http://filestoresg1.beetalkmobile.com:8081/file/aa531aadf48a6193d9a13cd803c7cfa2"], "urls": [], "title": "\u6289\u64c7"}, "threadStatus": 0, "regionId": 886, "barStatus": 0, "barId": 704, "postBy": {"utc": 1489843746000, "level": 3, "location": "\u9ad8\u96c4\u5e02\u00b7\u53f0\u7063", "avatar": "http://filestoresg1.beetalkmobile.com:8081/file/-3828509366623763039", "name": "\u4e0d\u4f7f\u7528"}, "id": 5575298}
