{"forum": {"content": "\u8a50\u9a19\u4eba\u7684\u9322\uff0c\u898b\u5230\u8acb\u901a\u77e5", "images": ["http://filestoresg1.beetalkmobile.com:8081/file/0894c9adf981c68a45a435a13ae9bc8e", "http://filestoresg1.beetalkmobile.com:8081/file/ef57d02dfe0a097c005247f228ff5b3c", "http://filestoresg1.beetalkmobile.com:8081/file/558d8e32c5e7bb60a206291c0c1d93c6", "http://filestoresg1.beetalkmobile.com:8081/file/75a78a1692571f8ab9597af6d5f689fa"], "urls": [], "title": "\u9a19\u9322\uff0c\u517c\u8077\uff0c"}, "threadStatus": 0, "regionId": 886, "barStatus": 0, "barId": 792, "postBy": {"utc": 1483162695000, "level": 2, "location": "\u5f70\u5316\u7e23\u00b7\u53f0\u7063", "avatar": "http://filestoresg1.beetalkmobile.com:8081/file/-2770264605172885753", "name": "\u58de\u4eba"}, "id": 5131730}
