{"forum": {"content": "\u4f86\u5f35\u7167\u9a19\u5427\uff01<br />\u4e0d\u6703\u96f7\u7684\u4f86\u8ddf\u6211\u4f86\u5834\u50b3\u8aaa\u5427\uff01<br />ID:\u62ff\u9435\u4e00\u676f\u4e0d\u52a0\u7cd6", "images": ["http://filestoresg1.beetalkmobile.com:8081/file/4b711788da37e919653c704b951a4141", "http://filestoresg1.beetalkmobile.com:8081/file/3c8af6f66ebf16c021a9217994fcd3d9", "http://filestoresg1.beetalkmobile.com:8081/file/e827b0b2293ffe29525a6454b36e7e6f", "http://filestoresg1.beetalkmobile.com:8081/file/2b648f5573ab8f46677af0a9a9eeecb5", "http://filestoresg1.beetalkmobile.com:8081/file/95468752210f84b3bc3387d492a3e510", "http://filestoresg1.beetalkmobile.com:8081/file/39407ea9f0b9ae52068de829ce027189"], "urls": [], "title": "\u4f60\u597d\uff0c\u6211\u4eca\u5e7424\u6b72"}, "threadStatus": 0, "regionId": 886, "barStatus": 0, "barId": 33, "postBy": {"utc": 1487238284000, "level": 4, "location": "\u9ad8\u96c4\u5e02\u00b7\u53f0\u7063", "avatar": "http://filestoresg1.beetalkmobile.com:8081/file/8149548300432292864", "name": "\u82b8\u82b8\u2764\ufe0f"}, "id": 5402551}
