{"forum": {"content": "\u5feb\u4f86\u804a\u5929\u54e6~", "images": ["http://filestoresg1.beetalkmobile.com:8081/file/e67567ae3ca8232ca578a57c8ceeed20", "http://filestoresg1.beetalkmobile.com:8081/file/574ea74e7166bffda8d6ea975e4cbcbb"], "urls": [], "title": "\u6709\u4eba\u6536\u55ce"}, "threadStatus": 0, "regionId": 886, "barStatus": 0, "barId": 205, "postBy": {"utc": 1487240532000, "level": 1, "location": "\u5f70\u5316\u7e23\u00b7\u53f0\u7063", "avatar": "http://filestoresg1.beetalkmobile.com:8081/file/-35786903112203963", "name": "\u5c0f\u98af"}, "id": 5402709}
