{"forum": {"content": "2\u67081\u65e5 \u6c34\u74f6<br /><br />\u6709\u4eba\u8981+1\u55ce", "images": ["http://filestoresg1.beetalkmobile.com:8081/file/84d819f0a6ff0d6fc383bb5b94e9a902"], "urls": [], "title": "2\u67081\u65e5 \u6c34\u74f6"}, "threadStatus": 1, "regionId": 886, "barStatus": 0, "barId": 765, "postBy": {"utc": 1483854363000, "level": 0, "location": "\u9ad8\u96c4\u5e02\u00b7\u53f0\u7063", "avatar": "http://filestoresg1.beetalkmobile.com:8081/file/-8001645944834333585", "name": "\u8317"}, "id": 5177771}
