{"forum": {"content": "\u6211\u7684\u5973\u670b\u53cb\u59b3\u6389\u5728\u54ea\u88e1\ud83d\ude26", "images": ["http://filestoresg1.beetalkmobile.com:8081/file/d673d16d30041ceb11fa16285d60c257"], "urls": [], "title": "\ud83d\ude2f\ud83d\ude2f\ud83d\ude2f"}, "threadStatus": 1, "regionId": 886, "barStatus": 0, "barId": 205, "postBy": {"utc": 1481650767000, "level": 9, "location": "\u53f0\u5317\u5e02\u00b7\u53f0\u7063", "avatar": "http://filestoresg1.beetalkmobile.com:8081/file/2306459836162835968", "name": "\ud83d\ude44"}, "id": 5032403}
