{"forum": {"content": "\u9019\u662f\u6211\u54e5\u54e5\u7684\u8ecd\u5916\u5957<br />\u7a7f\u8d77\u4f86\u6709\u4e00\u9ede\u6f6e\u6d41\u7684\u611f\u89ba<br />\u54c8\u54c8\u54c8\u54c8 \u597d\u5566\u6709\u9ede\u591a\u4e86", "images": ["http://filestoresg1.beetalkmobile.com:8081/file/5d39688f1677c765a5e6299d780d3434"], "urls": [], "title": "\u5098\u5175"}, "threadStatus": 1, "regionId": 886, "barStatus": 0, "barId": 704, "postBy": {"utc": 1491842277000, "level": 2, "location": "\u5c4f\u6771\u7e23\u00b7\u53f0\u7063", "avatar": "http://filestoresg1.beetalkmobile.com:8081/file/7459774095716973930", "name": "\u963f\u59b9\u59b9"}, "id": 5712710}
